Test/Ms.py
Test/__init__.py
aimaxcli-4.5.1.2021072201.dist-info/DESCRIPTION.rst
aimaxcli-4.5.1.2021072201.dist-info/METADATA
aimaxcli-4.5.1.2021072201.dist-info/RECORD
aimaxcli-4.5.1.2021072201.dist-info/WHEEL
aimaxcli-4.5.1.2021072201.dist-info/entry_points.txt
aimaxcli-4.5.1.2021072201.dist-info/metadata.json
aimaxcli-4.5.1.2021072201.dist-info/namespace_packages.txt
aimaxcli-4.5.1.2021072201.dist-info/top_level.txt
aimaxcmd/__init__.py
aimaxcmd/cmds.py
aimaxcmd/cmds_base.py
aimaxcmd/cmds_common.py
aimaxcmd/cmds_common_bk.py
aimaxcmd/cmds_image.py
aimaxcmd/cmds_node.py
aimaxcmd/cmds_user.py
aimaxcmd/cmds_yml.py
aimaxcmd/cmds_zone.py
aimaxcmd/cmds_zone_com.py
aimaxcmd/com-618.py
aimaxcmd/com-619.py
aimaxcmd/com.py
aimaxcmd/com714.py
aimaxcmd/com_716.py
aimaxcmd/com_batch.py
aimaxcmd/com_fuc.py
aimaxcmd/com_list.py
aimaxcmd/hello.py
aimaxcmd/main.py
aimaxcmd/yml.py
aimaxcmd/yml_715.py
aimaxcmd/yml_list.py
aimaxsdk/__init__.py
aimaxsdk/auth.py
aimaxsdk/errors.json
aimaxsdk/errors.py
aimaxsdk/tool.py
cliffdemo/__init__.py
cliffdemo/__main__.py
cliffdemo/encoding.py
cliffdemo/hook.py
cliffdemo/list.py
cliffdemo/main.py
cliffdemo/show.py
cliffdemo/simple.py
cmd/__init__.py
cmd/hello.py
cmd/main.py
sdk/__init__.py
sdk/auth.py
sdk/errors.py
sdk/tool.py
