Metadata-Version: 2.0
Name: aimaxcli
Version: 4.5.1.2021072201
Summary: AIMax python commands client
Home-page: UNKNOWN
Author: Gavin Li
Author-email: gavin_li@amaxgs.com
License: UNKNOWN
Platform: Any
Classifier: Development Status :: 3 - Alpha
Classifier: License :: OSI Approved :: Apache Software License
Classifier: Programming Language :: Python
Classifier: Programming Language :: Python :: 2
Classifier: Programming Language :: Python :: 2.7
Classifier: Programming Language :: Python :: 3
Classifier: Programming Language :: Python :: 3.2
Classifier: Intended Audience :: Developers
Classifier: Environment :: Console
Requires-Dist: cliff
Requires-Dist: requests
